chaintrailapi/__init__.py
chaintrailapi/accounts.py
chaintrailapi/dataset.py
chaintrailapi-0.0.6.dist-info/LICENSE
chaintrailapi-0.0.6.dist-info/METADATA
chaintrailapi-0.0.6.dist-info/WHEEL
chaintrailapi-0.0.6.dist-info/top_level.txt
chaintrailapi-0.0.6.dist-info/RECORD
