Metadata-Version: 2.1
Name: chaintrailapi
Version: 0.0.6
Summary: A small example package
Home-page: https://github.com/crcresearch/chaintrailapi
Author: University of Notre Dame, Center for Research Computing
Author-email: CRCsupport@nd.edu
License: UNKNOWN
Platform: UNKNOWN
Classifier: Programming Language :: Python :: 3
Classifier: License :: OSI Approved :: MIT License
Classifier: Operating System :: OS Independent
Requires-Dist: numpy
Requires-Dist: pandas
Requires-Dist: sklearn
Requires-Dist: matplotlib
Requires-Dist: requests-toolbelt
